asgi_tools-1.4.0.dist-info/RECORD
asgi_tools-1.4.0.dist-info/WHEEL
asgi_tools-1.4.0.dist-info/top_level.txt
asgi_tools-1.4.0.dist-info/METADATA
asgi_tools-1.4.0.dist-info/licenses/LICENSE
asgi_tools/multipart.py
asgi_tools/multipart.pyx
asgi_tools/forms.c
asgi_tools/multipart.c
asgi_tools/constants.py
asgi_tools/request.py
asgi_tools/__init__.py
asgi_tools/response.py
asgi_tools/types.py
asgi_tools/forms.cpython-313-darwin.so
asgi_tools/forms.py
asgi_tools/view.py
asgi_tools/utils.py
asgi_tools/logs.py
asgi_tools/multipart.cpython-313-darwin.so
asgi_tools/app.py
asgi_tools/py.typed
asgi_tools/errors.py
asgi_tools/multipart.pxd
asgi_tools/forms.pyx
asgi_tools/router.py
asgi_tools/_compat.py
asgi_tools/tests.py
asgi_tools/middleware.py
