Metadata-Version: 2.4
Name: asgi-tools
Version: 1.4.0
Summary: ASGI Toolkit to build web applications
Author-email: Kirill Klenov <horneds@gmail.com>
License: MIT License
Project-URL: homepage, https://github.com/klen/asgi-tools
Project-URL: repository, https://github.com/klen/asgi-tools
Project-URL: documentation, https://klen.github.io/asgi-tools
Keywords: asgi,asgi-tools,request,response,asyncio,trio
Classifier: Development Status :: 5 - Production/Stable
Classifier: Intended Audience :: Developers
Classifier: License :: OSI Approved :: MIT License
Classifier: Programming Language :: Python
Classifier: Programming Language :: Python :: 3
Classifier: Programming Language :: Python :: 3.10
Classifier: Programming Language :: Python :: 3.11
Classifier: Programming Language :: Python :: 3.12
Classifier: Programming Language :: Python :: 3.13
Classifier: Programming Language :: Python :: 3.14
Classifier: Programming Language :: Python :: Implementation :: PyPy
Classifier: Programming Language :: Cython
Classifier: Topic :: Internet :: WWW/HTTP
Classifier: Framework :: AsyncIO
Classifier: Framework :: Trio
Requires-Python: <4,>=3.10
License-File: LICENSE
Requires-Dist: http-router>=4.0.0
Requires-Dist: multidict>=6.6.3
Requires-Dist: sniffio
Requires-Dist: yarl>=1.8.2
Requires-Dist: async-timeout; python_version < "3.11"
Provides-Extra: tests
Requires-Dist: aiofile; extra == "tests"
Requires-Dist: pytest; extra == "tests"
Requires-Dist: pytest-aio[curio,trio]>=2; extra == "tests"
Requires-Dist: pytest-benchmark; extra == "tests"
Requires-Dist: PyYAML; extra == "tests"
Requires-Dist: ruff; extra == "tests"
Requires-Dist: mypy; extra == "tests"
Requires-Dist: exceptiongroup; python_version < "3.11" and extra == "tests"
Requires-Dist: ujson; implementation_name == "cpython" and extra == "tests"
Requires-Dist: uvloop; implementation_name == "cpython" and extra == "tests"
Requires-Dist: pytest-mypy; implementation_name == "cpython" and extra == "tests"
Provides-Extra: ujson
Requires-Dist: ujson; extra == "ujson"
Provides-Extra: orjson
Requires-Dist: orjson; extra == "orjson"
Provides-Extra: examples
Requires-Dist: uvicorn[standard]; extra == "examples"
Requires-Dist: jinja2; extra == "examples"
Requires-Dist: httpx; extra == "examples"
Provides-Extra: dev
Requires-Dist: bump2version; extra == "dev"
Requires-Dist: tox; extra == "dev"
Requires-Dist: cython; extra == "dev"
Requires-Dist: pre-commit; extra == "dev"
Requires-Dist: sphinx; extra == "dev"
Requires-Dist: pydata-sphinx-theme; extra == "dev"
Dynamic: license-file
